nginx_sso
