Metadata-Version: 1.1
Name: nginx-sso-dpaw
Version: 0.2rc1
Summary: Nginx SSO library for DPaW internal applications.
Home-page: https://bitbucket.org/dpaw/nginx-sso
Author: Rocky Chen
Author-email: asi@dpaw.wa.gov.au
License: BSD 3-Clause License
Keywords: auth,sso,nginx,dpaw
Platform: UNKNOWN
Classifier: Development Status :: 3 - Alpha
Classifier: Intended Audience :: Developers
Classifier: Intended Audience :: System Administrators
Classifier: License :: OSI Approved :: BSD License
Classifier: Programming Language :: Python
Classifier: Programming Language :: Python :: 2
Classifier: Programming Language :: Python :: 2.7
Classifier: Topic :: Software Development :: Libraries :: Python Modules
Classifier: Topic :: System :: Systems Administration :: Authentication/Directory
